zetastitcher/__init__.py
zetastitcher/version.py
zetastitcher/align/__init__.py
zetastitcher/align/__main__.py
zetastitcher/align/dog.py
zetastitcher/align/filematrix.py
zetastitcher/align/xcorr_filematrix.py
zetastitcher/fuse/__init__.py
zetastitcher/fuse/__main__.py
zetastitcher/fuse/absolute_positions.py
zetastitcher/fuse/fuse.py
zetastitcher/fuse/fuse_runner.py
zetastitcher/fuse/lcd_numbers.py
zetastitcher/fuse/overlaps.py
zetastitcher/fuse/virtual_fused_volume.py
zetastitcher/gaussian_stitcher/__init__.py
zetastitcher/gaussian_stitcher/common.py
zetastitcher/gaussian_stitcher/solver.py
zetastitcher/gaussian_stitcher/stitching.py
zetastitcher/gaussian_stitcher/utils.py
zetastitcher/gaussian_stitcher/linear/__init__.py
zetastitcher/gaussian_stitcher/linear/mapper.py
zetastitcher/gaussian_stitcher/linear/solver.py
zetastitcher/gaussian_stitcher/linear/stitching.py
zetastitcher/gaussian_stitcher/qp/__init__.py
zetastitcher/gaussian_stitcher/qp/mapper.py
zetastitcher/gaussian_stitcher/qp/stitching.py
zetastitcher/gaussian_stitcher/qp/util_debug.py
zetastitcher/io/__init__.py
zetastitcher/io/ffmpeg_wrapper.py
zetastitcher/io/inputfile.py
zetastitcher/io/inputfile_mixin.py
zetastitcher/io/mhdwrapper.py
zetastitcher/io/pims_wrapper.py
zetastitcher/io/tiffwrapper.py
zetastitcher/io/zipwrapper.py
zetastitcher/scripts/__init__.py
zetastitcher/scripts/stitch_downscale.py
zetastitcher-0.7.0.post1.dist-info/LICENSE.txt
zetastitcher-0.7.0.post1.dist-info/METADATA
zetastitcher-0.7.0.post1.dist-info/WHEEL
zetastitcher-0.7.0.post1.dist-info/entry_points.txt
zetastitcher-0.7.0.post1.dist-info/top_level.txt
zetastitcher-0.7.0.post1.dist-info/RECORD
