Metadata-Version: 2.1
Name: zetastitcher
Version: 0.7.0.post1
Summary: ZetaStitcher is a tool designed to stitch large volumetric images such as those produced by Light-Sheet Fluorescence Microscopes.
Home-page: https://github.com/lens-biophotonics/ZetaStitcher
Author: Giacomo Mazzamuto
Author-email: mazzamuto@lens.unifi.it
License: GPLv3+
Keywords: stitch,microscopy
Platform: UNKNOWN
Classifier: Development Status :: 3 - Alpha
Classifier: Intended Audience :: Science/Research
Classifier: Topic :: Scientific/Engineering
Classifier: License :: OSI Approved :: GNU General Public License v3 or later (GPLv3+)
Classifier: Programming Language :: Python :: 3.3
Classifier: Programming Language :: Python :: 3.4
Classifier: Programming Language :: Python :: 3.5
Classifier: Programming Language :: Python :: 3.6
Requires-Dist: cachetools
Requires-Dist: coloredlogs
Requires-Dist: cvxpy
Requires-Dist: humanize
Requires-Dist: imageio
Requires-Dist: networkx (>=2.0)
Requires-Dist: numpy
Requires-Dist: opencv-python
Requires-Dist: pandas
Requires-Dist: pims
Requires-Dist: psutil
Requires-Dist: pyyaml
Requires-Dist: qpsolvers
Requires-Dist: scipy
Requires-Dist: tifffile
Provides-Extra: dcimg
Requires-Dist: dcimg (>=0.4.0) ; extra == 'dcimg'
Provides-Extra: dev
Requires-Dist: pip-tools ; extra == 'dev'
Provides-Extra: doc
Requires-Dist: m2r2 ; extra == 'doc'
Requires-Dist: numpydoc ; extra == 'doc'
Requires-Dist: sphinx ; extra == 'doc'
Requires-Dist: sphinx-rtd-theme ; extra == 'doc'
Provides-Extra: test
Requires-Dist: mock ; extra == 'test'
